<?xml version="1.0" encoding="UTF-8" ?>
<!DOCTYPE mapper PUBLIC "-//mybatis.org//DTD Mapper 3.0//EN"
        "http://mybatis.org/dtd/mybatis-3-mapper.dtd">
<mapper namespace="jgs.bluemix.sample.repository.ProductMapper">

    <select id="findAllStockProducts" resultMap="productResultMap">
        SELECT
          product.id as product_id,
          product.item_code as product_item_code,
          product.item_name as product_item_name,
          product.price as product_price,
          product.detail as product_detail,
          product.create_date as product_create_date,
          product.update_date as product_update_date,
          product.version as product_version,
          stock.id as stock_id,
          stock.stock as stock_stock,
          stock.product_id as stock_product_id,
          stock.create_date as stock_create_date,
          stock.update_date as stock_update_date,
          stock.version as stock_version
        FROM
          product
          INNER JOIN stock ON product.id = stock.product_id
        WHERE
          stock.stock > 0
        ORDER BY
          product.item_code ASC
    </select>
    
    <select id="findProductPic" resultMap="productPicResultMap">
        SELECT pic.id, pic.pic, pic.create_date, pic.update_date, pic.version
        FROM
          product
          INNER JOIN product_pic pic on product.id = pic.product_id
        WHERE product.item_code = #{itemCode}
    </select>

    <resultMap id="productResultMap" type="jgs.bluemix.sample.entity.Product">
        <id property="id" column="product_id" />
        <result property="itemCode" column="product_item_code" />
        <result property="itemName" column="product_item_name" />
        <result property="price" column="product_price" />
        <result property="detail" column="product_detail" />
        <result property="createDate" column="product_create_date" />
        <result property="updateDate" column="product_update_date" />
        <result property="version" column="product_version" />
        <association property="stock" resultMap="stockResultMap" />
    </resultMap>

    <resultMap id="productPicResultMap" type="jgs.bluemix.sample.entity.ProductPic">
        <id property="id" column="id" />
        <result property="pic" column="pic" />
        <result property="createDate" column="create_date" />
        <result property="updateDate" column="update_date" />
        <result property="version" column="version" />
    </resultMap>

    <resultMap id="stockResultMap" type="jgs.bluemix.sample.entity.Stock">
        <id property="id" column="stock_id" />
        <result property="stock" column="stock_stock" />
        <result property="createDate" column="stock_create_date" />
        <result property="updateDate" column="stock_update_date" />
        <result property="version" column="stock_version" />
        <association property="product" resultMap="productResultMap" />
    </resultMap>

</mapper>